var lopcodes_8h =
[
    [ "BITRK", "d0/da7/lopcodes_8h.html#ab8d4f5d2db10dd5b3c15e0081596e41c", null ],
    [ "CREATE_ABC", "d0/da7/lopcodes_8h.html#a847467d29d9430a3a869e99952350b2d", null ],
    [ "CREATE_ABx", "d0/da7/lopcodes_8h.html#a46bb00b89420c78407eb45a3bc98b50d", null ],
    [ "CREATE_Ax", "d0/da7/lopcodes_8h.html#ae08e838d4e7f9c8ed9b23a6a52d1b819", null ],
    [ "GET_OPCODE", "d0/da7/lopcodes_8h.html#aaa146179c3677b790c5681dcd82f0acc", null ],
    [ "getarg", "d0/da7/lopcodes_8h.html#a34176ea971e0563a800c45073da2d09a", null ],
    [ "GETARG_A", "d0/da7/lopcodes_8h.html#a1d504abc1e2246548f89977210dce0b9", null ],
    [ "GETARG_Ax", "d0/da7/lopcodes_8h.html#acfd578bba038b6682b924cf48012d80a", null ],
    [ "GETARG_B", "d0/da7/lopcodes_8h.html#a7a343159ef7669a438c2097b839b2b13", null ],
    [ "GETARG_Bx", "d0/da7/lopcodes_8h.html#acf8d228275fd2789dcf5f019bbabc019", null ],
    [ "GETARG_C", "d0/da7/lopcodes_8h.html#af96cb84f2685fda7f36d3d099dba6a44", null ],
    [ "GETARG_sBx", "d0/da7/lopcodes_8h.html#a1f61a823709ac7847e481290a596c480", null ],
    [ "getBMode", "d0/da7/lopcodes_8h.html#af4588c163e23efaa97976d30c94d89b4", null ],
    [ "getCMode", "d0/da7/lopcodes_8h.html#aa2535ccc1080a3705abfc0b1061b281e", null ],
    [ "getOpMode", "d0/da7/lopcodes_8h.html#afb3fdd221fb95fdd1c254f7ab479739e", null ],
    [ "INDEXK", "d0/da7/lopcodes_8h.html#ab5017051e99e0a98e021863757bb2228", null ],
    [ "ISK", "d0/da7/lopcodes_8h.html#a143ea69a87f0463de7a856da4dd612e2", null ],
    [ "LFIELDS_PER_FLUSH", "d0/da7/lopcodes_8h.html#a0888e2bcb54f6e603f09208763aadfe9", null ],
    [ "MASK0", "d0/da7/lopcodes_8h.html#ac38be540eada841367170e3764e93748", null ],
    [ "MASK1", "d0/da7/lopcodes_8h.html#aedd5e7a7ce381d9be03d198dce7db53f", null ],
    [ "MAXARG_A", "d0/da7/lopcodes_8h.html#ab3c4feecc8cd0add12e881e26bbb3b15", null ],
    [ "MAXARG_Ax", "d0/da7/lopcodes_8h.html#a742a1bed832225c3800b3f73eb8b20ec", null ],
    [ "MAXARG_B", "d0/da7/lopcodes_8h.html#ae5132046fa2196de46214613a36235b2", null ],
    [ "MAXARG_Bx", "d0/da7/lopcodes_8h.html#aebbf650de6e9cbec539bfabcb9ae50c6", null ],
    [ "MAXARG_C", "d0/da7/lopcodes_8h.html#a15a7daf14e4640990519e4e7f627900f", null ],
    [ "MAXARG_sBx", "d0/da7/lopcodes_8h.html#a076bbd704fe8773693851f82d82206a6", null ],
    [ "MAXINDEXRK", "d0/da7/lopcodes_8h.html#a37cd6e85943ea87c9b99ef1ea6bcdb3e", null ],
    [ "NO_REG", "d0/da7/lopcodes_8h.html#a6552ce4b3bba3b1a820dc0adaf85974a", null ],
    [ "NUM_OPCODES", "d0/da7/lopcodes_8h.html#a1fb469ba81540d3314cfbe37c675ba20", null ],
    [ "POS_A", "d0/da7/lopcodes_8h.html#a9a088c55af7f419a19a3228fd5048ef7", null ],
    [ "POS_Ax", "d0/da7/lopcodes_8h.html#a1df1ba0f129f8e4691da2c5e6d1ecc39", null ],
    [ "POS_B", "d0/da7/lopcodes_8h.html#ac71a05d32f83f3f83b05fa95bad8c953", null ],
    [ "POS_Bx", "d0/da7/lopcodes_8h.html#a3626b235301aa4d50a1eddfb650ddd87", null ],
    [ "POS_C", "d0/da7/lopcodes_8h.html#ab67ab8adf1f91e2c7e2b30b5345d214d", null ],
    [ "POS_OP", "d0/da7/lopcodes_8h.html#a86559e8fac93f9aa28733fc4dd96af51", null ],
    [ "RKASK", "d0/da7/lopcodes_8h.html#a16493800cf7e5cbdc549add83484a750", null ],
    [ "SET_OPCODE", "d0/da7/lopcodes_8h.html#a9ae2b84a40beacf053969ff426aae06f", null ],
    [ "setarg", "d0/da7/lopcodes_8h.html#afb6645a4d916d7dab36ba5f6f658bb8a", null ],
    [ "SETARG_A", "d0/da7/lopcodes_8h.html#a01900876b9281238c6dbb4d7bc59ca66", null ],
    [ "SETARG_Ax", "d0/da7/lopcodes_8h.html#afeb0c89bdd47db50d0ba6b78bc894681", null ],
    [ "SETARG_B", "d0/da7/lopcodes_8h.html#a52ddcdcbd367c4557cc83c38e3e1723f", null ],
    [ "SETARG_Bx", "d0/da7/lopcodes_8h.html#a0c476ba8d647ec398f25bb6374a0c088", null ],
    [ "SETARG_C", "d0/da7/lopcodes_8h.html#a085f9af93bc2386ddb0b9fb53d5ff0b8", null ],
    [ "SETARG_sBx", "d0/da7/lopcodes_8h.html#ad28b4bc013c6ddae165ac998ebe321c7", null ],
    [ "SIZE_A", "d0/da7/lopcodes_8h.html#a205e8f662c5b2496cb7d9e7aa37cda90", null ],
    [ "SIZE_Ax", "d0/da7/lopcodes_8h.html#a52d077faf8699f2d66aef36bf4e6c751", null ],
    [ "SIZE_B", "d0/da7/lopcodes_8h.html#ac8795820709810bf0baf1660341cacc2", null ],
    [ "SIZE_Bx", "d0/da7/lopcodes_8h.html#a4b81cf762841df8820b6077b66c0c619", null ],
    [ "SIZE_C", "d0/da7/lopcodes_8h.html#a5f42703bf77b09689626ca8cf3fc5fc1", null ],
    [ "SIZE_OP", "d0/da7/lopcodes_8h.html#a4c1d995d13200130d713c6dc5e223c13", null ],
    [ "testAMode", "d0/da7/lopcodes_8h.html#aaae51a1c7e304923c51509b7cd644f29", null ],
    [ "testTMode", "d0/da7/lopcodes_8h.html#a6750851f9d04ae7f9612146b07f88c97", null ],
    [ "OpArgMask", "d0/da7/lopcodes_8h.html#a74ef10b1841536b2ae065f2371fb9436", [
      [ "OpArgN", "d0/da7/lopcodes_8h.html#a74ef10b1841536b2ae065f2371fb9436a62f4c828039f757e4eb8ec28754e27ac", null ],
      [ "OpArgU", "d0/da7/lopcodes_8h.html#a74ef10b1841536b2ae065f2371fb9436a590dbd8a54a83dc0480430b12e9e792d", null ],
      [ "OpArgR", "d0/da7/lopcodes_8h.html#a74ef10b1841536b2ae065f2371fb9436a1704c8739c8e44d4a28d98cf4dc1cd1f", null ],
      [ "OpArgK", "d0/da7/lopcodes_8h.html#a74ef10b1841536b2ae065f2371fb9436ad365ba9de2ad41c5962f29b1edbf3fd2", null ]
    ] ],
    [ "OpCode", "d0/da7/lopcodes_8h.html#abeb7dfb0e9e2b3114e240a405d046ea7", [
      [ "OP_MOVE", "d0/da7/lopcodes_8h.html#abeb7dfb0e9e2b3114e240a405d046ea7addf83bbc02b6a88d325135c880d12184", null ],
      [ "OP_LOADK", "d0/da7/lopcodes_8h.html#abeb7dfb0e9e2b3114e240a405d046ea7ab34a8eaf6d32d3c41810653d9eb99c1a", null ],
      [ "OP_LOADKX", "d0/da7/lopcodes_8h.html#abeb7dfb0e9e2b3114e240a405d046ea7ae95580de7b3877b66fdf87366b8e5887", null ],
      [ "OP_LOADBOOL", "d0/da7/lopcodes_8h.html#abeb7dfb0e9e2b3114e240a405d046ea7af5f66d1583580293a60f96a26770e5ba", null ],
      [ "OP_LOADNIL", "d0/da7/lopcodes_8h.html#abeb7dfb0e9e2b3114e240a405d046ea7a5c399a98a26c923cdae3971b5e5b6432", null ],
      [ "OP_GETUPVAL", "d0/da7/lopcodes_8h.html#abeb7dfb0e9e2b3114e240a405d046ea7ab48573533495922f053a7d1c9b0d00b4", null ],
      [ "OP_GETTABUP", "d0/da7/lopcodes_8h.html#abeb7dfb0e9e2b3114e240a405d046ea7acba90301f3ac979a3edd23f74182367b", null ],
      [ "OP_GETTABLE", "d0/da7/lopcodes_8h.html#abeb7dfb0e9e2b3114e240a405d046ea7ab1ec2a36c59db7612249cc31e382fdd9", null ],
      [ "OP_SETTABUP", "d0/da7/lopcodes_8h.html#abeb7dfb0e9e2b3114e240a405d046ea7ac486cd83792b58a638e37cb249d54a7e", null ],
      [ "OP_SETUPVAL", "d0/da7/lopcodes_8h.html#abeb7dfb0e9e2b3114e240a405d046ea7a47df60373847890b47b447c870aea678", null ],
      [ "OP_SETTABLE", "d0/da7/lopcodes_8h.html#abeb7dfb0e9e2b3114e240a405d046ea7a34315d7408f31b006bf41c9e9c2d736e", null ],
      [ "OP_NEWTABLE", "d0/da7/lopcodes_8h.html#abeb7dfb0e9e2b3114e240a405d046ea7af4ae9eb9a3c88596112a1d99d0c66280", null ],
      [ "OP_SELF", "d0/da7/lopcodes_8h.html#abeb7dfb0e9e2b3114e240a405d046ea7a64bea18253f9e73c4c5fcfa6b0d5abd2", null ],
      [ "OP_ADD", "d0/da7/lopcodes_8h.html#abeb7dfb0e9e2b3114e240a405d046ea7a96186829480e5b34b1373288e956b1c8", null ],
      [ "OP_SUB", "d0/da7/lopcodes_8h.html#abeb7dfb0e9e2b3114e240a405d046ea7a6c224b456bd394d4d8bad0631ca8e2b7", null ],
      [ "OP_MUL", "d0/da7/lopcodes_8h.html#abeb7dfb0e9e2b3114e240a405d046ea7aa0e08a6f94350f03d29e4a55d543ba2f", null ],
      [ "OP_DIV", "d0/da7/lopcodes_8h.html#abeb7dfb0e9e2b3114e240a405d046ea7a719aeab2140dd5f575d1559b95bf74e1", null ],
      [ "OP_MOD", "d0/da7/lopcodes_8h.html#abeb7dfb0e9e2b3114e240a405d046ea7a39c596fc7eae450b7218bd97126e37c9", null ],
      [ "OP_POW", "d0/da7/lopcodes_8h.html#abeb7dfb0e9e2b3114e240a405d046ea7a35127684be890cfd81d556dc84d5f9db", null ],
      [ "OP_UNM", "d0/da7/lopcodes_8h.html#abeb7dfb0e9e2b3114e240a405d046ea7ae3fd0932f8be8e5e810d731fd60ab8ef", null ],
      [ "OP_NOT", "d0/da7/lopcodes_8h.html#abeb7dfb0e9e2b3114e240a405d046ea7a36a6b73cc4823f54891a013e2cc760d1", null ],
      [ "OP_LEN", "d0/da7/lopcodes_8h.html#abeb7dfb0e9e2b3114e240a405d046ea7a55406931f4958f887e6d966d154a1931", null ],
      [ "OP_CONCAT", "d0/da7/lopcodes_8h.html#abeb7dfb0e9e2b3114e240a405d046ea7a28a7da14b1413b441cf2a5d433b43a51", null ],
      [ "OP_JMP", "d0/da7/lopcodes_8h.html#abeb7dfb0e9e2b3114e240a405d046ea7afd679fab86e6a91d22c91734e287639b", null ],
      [ "OP_EQ", "d0/da7/lopcodes_8h.html#abeb7dfb0e9e2b3114e240a405d046ea7a1634898deb6e4d1bcb15416034c641c5", null ],
      [ "OP_LT", "d0/da7/lopcodes_8h.html#abeb7dfb0e9e2b3114e240a405d046ea7a7d5ed006824d331041dad8486e52df50", null ],
      [ "OP_LE", "d0/da7/lopcodes_8h.html#abeb7dfb0e9e2b3114e240a405d046ea7acef6e71b662db063ff532d89500bb0c0", null ],
      [ "OP_TEST", "d0/da7/lopcodes_8h.html#abeb7dfb0e9e2b3114e240a405d046ea7a8952e66300f2660060e38c67ccd21c9d", null ],
      [ "OP_TESTSET", "d0/da7/lopcodes_8h.html#abeb7dfb0e9e2b3114e240a405d046ea7a39b4077a15fb8fffc166f5045dddacee", null ],
      [ "OP_CALL", "d0/da7/lopcodes_8h.html#abeb7dfb0e9e2b3114e240a405d046ea7a098bbeea13096667b102f7fd90cbe38f", null ],
      [ "OP_TAILCALL", "d0/da7/lopcodes_8h.html#abeb7dfb0e9e2b3114e240a405d046ea7aff2c07ebfd82aa22cc247e9855a16069", null ],
      [ "OP_RETURN", "d0/da7/lopcodes_8h.html#abeb7dfb0e9e2b3114e240a405d046ea7ad436c18b194473f5ec64c28b774e41b3", null ],
      [ "OP_FORLOOP", "d0/da7/lopcodes_8h.html#abeb7dfb0e9e2b3114e240a405d046ea7aa01470a2fc70a3f2dbd20c7c8f270802", null ],
      [ "OP_FORPREP", "d0/da7/lopcodes_8h.html#abeb7dfb0e9e2b3114e240a405d046ea7a5277c6eb2b1ab790c4942fdccd749e33", null ],
      [ "OP_TFORCALL", "d0/da7/lopcodes_8h.html#abeb7dfb0e9e2b3114e240a405d046ea7a899602d2c96443e08eec9e477071aa22", null ],
      [ "OP_TFORLOOP", "d0/da7/lopcodes_8h.html#abeb7dfb0e9e2b3114e240a405d046ea7a7dabccd7671c8ff374cb4502a6edb9c0", null ],
      [ "OP_SETLIST", "d0/da7/lopcodes_8h.html#abeb7dfb0e9e2b3114e240a405d046ea7a01618d8295953fd4ab2ef721b2051718", null ],
      [ "OP_CLOSURE", "d0/da7/lopcodes_8h.html#abeb7dfb0e9e2b3114e240a405d046ea7a407a76cd8c503b0f4dc14603687a77a2", null ],
      [ "OP_VARARG", "d0/da7/lopcodes_8h.html#abeb7dfb0e9e2b3114e240a405d046ea7a1856103c50818d72aaa506821a4ef004", null ],
      [ "OP_EXTRAARG", "d0/da7/lopcodes_8h.html#abeb7dfb0e9e2b3114e240a405d046ea7ae7a29a9b5e1490453da04cba95b39bea", null ]
    ] ],
    [ "OpMode", "d0/da7/lopcodes_8h.html#a56752d1aeb4bd4940e632396072d68af", [
      [ "iABC", "d0/da7/lopcodes_8h.html#a56752d1aeb4bd4940e632396072d68afa5032b5bab05a3312f6236ad8a6053cf3", null ],
      [ "iABx", "d0/da7/lopcodes_8h.html#a56752d1aeb4bd4940e632396072d68afae162f330f7a1e7581cdbbb4af60dc8ea", null ],
      [ "iAsBx", "d0/da7/lopcodes_8h.html#a56752d1aeb4bd4940e632396072d68afa5db94456d16691b254a6b2fc7b473e55", null ],
      [ "iAx", "d0/da7/lopcodes_8h.html#a56752d1aeb4bd4940e632396072d68afa453db051897b5faf2716653c2aa5a2e2", null ]
    ] ],
    [ "luaP_opmodes", "d0/da7/lopcodes_8h.html#a4db2b7826fc1923c98df7edbe8828be6", null ],
    [ "luaP_opnames", "d0/da7/lopcodes_8h.html#ae10cd77813f45aae4f7ea2fe3fed8edd", null ]
];